gpulurker/__init__.py
gpulurker/gpustat.py
gpulurker/main.py
gpulurker/util.py
gpulurker-0.1.dist-info/LICENSE
gpulurker-0.1.dist-info/METADATA
gpulurker-0.1.dist-info/WHEEL
gpulurker-0.1.dist-info/entry_points.txt
gpulurker-0.1.dist-info/top_level.txt
gpulurker-0.1.dist-info/RECORD
