Metadata-Version: 2.1
Name: gpulurker
Version: 0.1
Summary: An interactive NVIDIA-GPU process viewer.
Home-page: https://github.com/RenShuhuai-Andy/gpu_lurker.git
Author: Shuhuai Ren
Author-email: renshuhuai007@gmail.com
License: GPLv3
Project-URL: Bug Reports, https://github.com/RenShuhuai-Andy/gpu_lurker/issues
Project-URL: Source, https://github.com/RenShuhuai-Andy/gpu_lurker
Keywords: nvidia,nvidia-smi,GPU,wechat,htop
Platform: UNKNOWN
Classifier: Development Status :: 4 - Beta
Classifier: License :: OSI Approved :: GNU General Public License v3 (GPLv3)
Classifier: Programming Language :: Python :: 3 :: Only
Classifier: Programming Language :: Python :: 3.5
Classifier: Programming Language :: Python :: 3.6
Classifier: Programming Language :: Python :: 3.7
Classifier: Programming Language :: Python :: 3.8
Classifier: Programming Language :: Python :: 3.9
Classifier: Operating System :: Microsoft :: Windows
Classifier: Operating System :: POSIX :: Linux
Classifier: Environment :: GPU
Classifier: Environment :: Console
Classifier: Environment :: Console :: Curses
Classifier: Intended Audience :: Developers
Classifier: Intended Audience :: End Users/Desktop
Classifier: Intended Audience :: System Administrators
Classifier: Topic :: System :: Hardware
Classifier: Topic :: System :: Monitoring
Classifier: Topic :: System :: Systems Administration
Classifier: Topic :: Utilities
Requires-Python: >=3.5, <4
Requires-Dist: pynvml
Requires-Dist: blessed
Requires-Dist: apscheduler
Requires-Dist: requests
Requires-Dist: argparse
